cospgd/__init__.py
cospgd/attack_implementations.py
cospgd-0.1.3.dist-info/LICENSE.md
cospgd-0.1.3.dist-info/METADATA
cospgd-0.1.3.dist-info/WHEEL
cospgd-0.1.3.dist-info/top_level.txt
cospgd-0.1.3.dist-info/RECORD
