Metadata-Version: 2.1
Name: cospgd
Version: 0.1.3
Summary: A tool for benchmarking adversarial robustness of pixel-wise prediction tasks.
Home-page: https://github.com/shashankskagnihotri/cospgd
Author: Shashank Agnihotri, Steffen Jung, Prof. Dr. Margret Keuper
Author-email: shashanksagnihotri@gmail.com
License: MIT
Classifier: Development Status :: 5 - Production/Stable
Classifier: Intended Audience :: Science/Research
Classifier: License :: OSI Approved :: MIT License
Classifier: Natural Language :: English
Classifier: Operating System :: POSIX :: Linux
Classifier: Programming Language :: Python :: 3
Classifier: Programming Language :: Python :: 3.6
Classifier: Programming Language :: Python :: 3.7
Classifier: Programming Language :: Python :: 3.8
Classifier: Programming Language :: Python :: 3.9
Classifier: Programming Language :: Python :: 3.10
Classifier: Programming Language :: Python :: 3.11
Classifier: Topic :: Software Development :: Libraries :: Python Modules
License-File: LICENSE.md
Requires-Dist: torch (>=1.7)
Requires-Dist: numpy
